bbox_visualizer2/__init__.py
bbox_visualizer2/bbox_visualizer2.py
bbox_visualizer2-0.0.4.dist-info/METADATA
bbox_visualizer2-0.0.4.dist-info/WHEEL
bbox_visualizer2-0.0.4.dist-info/licenses/LICENSE
bbox_visualizer2-0.0.4.dist-info/RECORD
