Metadata-Version: 2.1
Name: bbox-visualizer2
Version: 0.0.4
Summary: A bounding box visualizer
Project-URL: Homepage, https://github.com/fansuregrin/bbox-visualizer2
Project-URL: Bug Tracker, https://github.com/fansuregrin/bbox-visualizer2/issues
Author-email: Fansure Grin <pwz113436@gmail.com>
License: MIT License
License-File: LICENSE
Keywords: bbox,object-detection,visualizer
Classifier: License :: OSI Approved :: MIT License
Classifier: Operating System :: OS Independent
Classifier: Programming Language :: Python :: 3
Requires-Python: >=3.7
Requires-Dist: numpy
Requires-Dist: pillow
